LICENSE.txt
MANIFEST.in
setup.py
aldryn_pypi_stats/__init__.py
aldryn_pypi_stats/admin.py
aldryn_pypi_stats/cms_plugins.py
aldryn_pypi_stats/models.py
aldryn_pypi_stats.egg-info/PKG-INFO
aldryn_pypi_stats.egg-info/SOURCES.txt
aldryn_pypi_stats.egg-info/dependency_links.txt
aldryn_pypi_stats.egg-info/not-zip-safe
aldryn_pypi_stats.egg-info/requires.txt
aldryn_pypi_stats.egg-info/top_level.txt
aldryn_pypi_stats/boilerplates/bootstrap3/templates/aldryn_pypi_stats/plugins/downloads.html
aldryn_pypi_stats/migrations/0001_initial.py
aldryn_pypi_stats/migrations/0002_pypistatsdownloadspluginmodel_base_count.py
aldryn_pypi_stats/migrations/__init__.py
aldryn_pypi_stats/south_migrations/0001_initial.py
aldryn_pypi_stats/south_migrations/0002_auto__add_field_pypistatsdownloadspluginmodel_upper_text__add_field_py.py
aldryn_pypi_stats/south_migrations/0003_auto__del_field_pypistatsdownloadspluginmodel_subhead__del_field_pypis.py
aldryn_pypi_stats/south_migrations/__init__.py